Workbook

Sheet Instructions
A1: ACME Company Accounting System Instructions
A3: How to use the accounting workbook
A5: 1. Enter journal entries in the Transactions sheet. Use the Account dropdown and enter amounts in Debit or Credit.
A6: 2. The Trial Balance sheet totals all debits and credits by account automatically.
A7: 3. The Income Statement calculates expenses and revenue automatically from account types.
A8: 4. The Balance Sheet shows asset, liability, and equity balances and verifies the accounting equation.
A9: 5. The Dashboard shows key totals and balance status at a glance.
A10: 6. Add new accounts in Chart_of_Accounts starting at row 4. Extend formulas if you add more than 15 accounts.
A12: Tips:
A13: - Keep dates sorted in Transactions for clear ledger balance behavior.
A14: - Use the Account dropdown to avoid spelling errors.
A15: - Add more rows in Transactions as needed; the system supports many entries.
A16: - Press F9 or reopen the workbook to force Excel to recalculate formulas if needed.

Sheet Chart_of_Accounts
A1: ACME Company Accounting System
A2: Chart of Accounts
A3: Account Code | B3: Account Name | C3: Type | D3: Normal Balance
A4: 1001 | B4: Cash | C4: Asset | D4: Debit
A5: 1002 | B5: Bank | C5: Asset | D5: Debit
A6: 1003 | B6: Accounts Receivable | C6: Asset | D6: Debit
A7: 1004 | B7: Inventory | C7: Asset | D7: Debit
A8: 1005 | B8: Equipment | C8: Asset | D8: Debit
A9: 1006 | B9: Land | C9: Asset | D9: Debit
A10: 1007 | B10: Buildings | C10: Asset | D10: Debit
A11: 1008 | B11: Machinery | C11: Asset | D11: Debit
A12: 2001 | B12: Accounts Payable | C12: Liability | D12: Credit
A13: 2002 | B13: Notes Payable | C13: Liability | D13: Credit
A14: 3001 | B14: Capital | C14: Equity | D14: Credit
A15: 3002 | B15: Retained Earnings | C15: Equity | D15: Credit
... A21: 5004 | B21: Supplies Expense | C21: Expense | D21: Debit

Sheet Transactions
A1: ACME Company Accounting System
A2: Transactions Journal
A3: Date | B3: Description | C3: Account | D3: Debit | E3: Credit | F3: Due Date | G3: Status | H3: Paid
G4: =IF($H4="Paid","Paid",IF(OR($F4="",NOT(ISNUMBER($F4))),"",IF(TODAY()>$F4,"Overdue","Pending")))
G5: =IF($H5="Paid","Paid",IF(OR($F5="",NOT(ISNUMBER($F5))),"",IF(TODAY()>$F5,"Overdue","Pending")))

Sheet General_Ledger
A1: ACME Company Accounting System
A2: General Ledger
A3: Date | B3: Description | C3: Account | D3: Debit | E3: Credit | F3: Balance
A4: =IF(Transactions!A4="","",Transactions!A4) | B4: =Transactions!B4 -> 0 | C4: =Transactions!C4 -> 0 | D4: =Transactions!D4 -> 0 | E4: =Transactions!E4 -> 0 | F4: =IF(OR($A4="",$C4=""),"",IF(VLOOKUP($C4,Chart_of_Accounts!$B:$D,3,0)="Debit",SUMIF(Transactions!$C:$C,$C4,Transactions!$D:$D)-SUMIF(Transactions!$C:$C,$C4,Transactions!$E:$E),SUMIF(Transactions!$C:$C,$C4,Transactions!$E:$E)-SUMIF(Transactions!$C:$C,$C4,Transactions!$D:$D)))
A5: =IF(Transactions!A5="","",Transactions!A5) | B5: =Transactions!B5 -> 0 | C5: =Transactions!C5 -> 0 | D5: =Transactions!D5 -> 0 | E5: =Transactions!E5 -> 0 | F5: =IF(OR($A5="",$C5=""),"",IF(VLOOKUP($C5,Chart_of_Accounts!$B:$D,3,0)="Debit",SUMIF(Transactions!$C:$C,$C5,Transactions!$D:$D)-SUMIF(Transactions!$C:$C,$C5,Transactions!$E:$E),SUMIF(Transactions!$C:$C,$C5,Transactions!$E:$E)-SUMIF(Transactions!$C:$C,$C5,Transactions!$D:$D)))
A6: =IF(Transactions!A6="","",Transactions!A6) | B6: =Transactions!B6 -> 0 | C6: =Transactions!C6 -> 0 | D6: =Transactions!D6 -> 0 | E6: =Transactions!E6 -> 0 | F6: =IF(OR($A6="",$C6=""),"",IF(VLOOKUP($C6,Chart_of_Accounts!$B:$D,3,0)="Debit",SUMIF(Transactions!$C:$C,$C6,Transactions!$D:$D)-SUMIF(Transactions!$C:$C,$C6,Transactions!$E:$E),SUMIF(Transactions!$C:$C,$C6,Transactions!$E:$E)-SUMIF(Transactions!$C:$C,$C6,Transactions!$D:$D)))
A7: =IF(Transactions!A7="","",Transactions!A7) | B7: =Transactions!B7 -> 0 | C7: =Transactions!C7 -> 0 | D7: =Transactions!D7 -> 0 | E7: =Transactions!E7 -> 0 | F7: =IF(OR($A7="",$C7=""),"",IF(VLOOKUP($C7,Chart_of_Accounts!$B:$D,3,0)="Debit",SUMIF(Transactions!$C:$C,$C7,Transactions!$D:$D)-SUMIF(Transactions!$C:$C,$C7,Transactions!$E:$E),SUMIF(Transactions!$C:$C,$C7,Transactions!$E:$E)-SUMIF(Transactions!$C:$C,$C7,Transactions!$D:$D)))
A8: =IF(Transactions!A8="","",Transactions!A8) | B8: =Transactions!B8 -> 0 | C8: =Transactions!C8 -> 0 | D8: =Transactions!D8 -> 0 | E8: =Transactions!E8 -> 0 | F8: =IF(OR($A8="",$C8=""),"",IF(VLOOKUP($C8,Chart_of_Accounts!$B:$D,3,0)="Debit",SUMIF(Transactions!$C:$C,$C8,Transactions!$D:$D)-SUMIF(Transactions!$C:$C,$C8,Transactions!$E:$E),SUMIF(Transactions!$C:$C,$C8,Transactions!$E:$E)-SUMIF(Transactions!$C:$C,$C8,Transactions!$D:$D)))
A9: =IF(Transactions!A9="","",Transactions!A9) | B9: =Transactions!B9 -> 0 | C9: =Transactions!C9 -> 0 | D9: =Transactions!D9 -> 0 | E9: =Transactions!E9 -> 0 | F9: =IF(OR($A9="",$C9=""),"",IF(VLOOKUP($C9,Chart_of_Accounts!$B:$D,3,0)="Debit",SUMIF(Transactions!$C:$C,$C9,Transactions!$D:$D)-SUMIF(Transactions!$C:$C,$C9,Transactions!$E:$E),SUMIF(Transactions!$C:$C,$C9,Transactions!$E:$E)-SUMIF(Transactions!$C:$C,$C9,Transactions!$D:$D)))
A10: =IF(Transactions!A10="","",Transactions!A10) | B10: =Transactions!B10 -> 0 | C10: =Transactions!C10 -> 0 | D10: =Transactions!D10 -> 0 | E10: =Transactions!E10 -> 0 | F10: =IF(OR($A4="",$C4=""),"",IF(VLOOKUP($C4,Chart_of_Accounts!$B:$D,3,0)="Debit",D4-E4,E4-D4))
A11: =IF(Transactions!A11="","",Transactions!A11) | B11: =Transactions!B11 -> 0 | C11: =Transactions!C11 -> 0 | D11: =Transactions!D11 -> 0 | E11: =Transactions!E11 -> 0 | F11: =IF(OR($A5="",$C5=""),"",IF($C5=$C4,F4+IF(VLOOKUP($C5,Chart_of_Accounts!$B:$D,3,0)="Debit",D5-E5,E5-D5),IF(VLOOKUP($C5,Chart_of_Accounts!$B:$D,3,0)="Debit",D5-E5,E5-D5)))
A12: =IF(Transactions!A12="","",Transactions!A12) | B12: =Transactions!B12 -> 0 | C12: =Transactions!C12 -> 0 | D12: =Transactions!D12 -> 0 | E12: =Transactions!E12 -> 0 | F12: =IF(OR($A6="",$C6=""),"",IF($C6=$C5,F5+IF(VLOOKUP($C6,Chart_of_Accounts!$B:$D,3,0)="Debit",D6-E6,E6-D6),IF(VLOOKUP($C6,Chart_of_Accounts!$B:$D,3,0)="Debit",D6-E6,E6-D6)))
A13: =IF(Transactions!A13="","",Transactions!A13) | B13: =Transactions!B13 -> 0 | C13: =Transactions!C13 -> 0 | D13: =Transactions!D13 -> 0 | E13: =Transactions!E13 -> 0 | F13: =IF(OR($A7="",$C7=""),"",IF($C7=$C6,F6+IF(VLOOKUP($C7,Chart_of_Accounts!$B:$D,3,0)="Debit",D7-E7,E7-D7),IF(VLOOKUP($C7,Chart_of_Accounts!$B:$D,3,0)="Debit",D7-E7,E7-D7)))
A14: =IF(Transactions!A14="","",Transactions!A14) | B14: =Transactions!B14 -> 0 | C14: =Transactions!C14 -> 0 | D14: =Transactions!D14 -> 0 | E14: =Transactions!E14 -> 0 | F14: =IF(OR($A8="",$C8=""),"",IF($C8=$C7,F7+IF(VLOOKUP($C8,Chart_of_Accounts!$B:$D,3,0)="Debit",D8-E8,E8-D8),IF(VLOOKUP($C8,Chart_of_Accounts!$B:$D,3,0)="Debit",D8-E8,E8-D8)))
A15: =IF(Transactions!A15="","",Transactions!A15) | B15: =Transactions!B15 -> 0 | C15: =Transactions!C15 -> 0 | D15: =Transactions!D15 -> 0 | E15: =Transactions!E15 -> 0 | F15: =IF(OR($A9="",$C9=""),"",IF($C9=$C8,F8+IF(VLOOKUP($C9,Chart_of_Accounts!$B:$D,3,0)="Debit",D9-E9,E9-D9),IF(VLOOKUP($C9,Chart_of_Accounts!$B:$D,3,0)="Debit",D9-E9,E9-D9)))
A16: =IF(Transactions!A16="","",Transactions!A16) | B16: =Transactions!B16 -> 0 | C16: =Transactions!C16 -> 0 | D16: =Transactions!D16 -> 0 | E16: =Transactions!E16 -> 0 | F16: =IF(OR($A10="",$C10=""),"",IF($C10=$C9,F9+IF(VLOOKUP($C10,Chart_of_Accounts!$B:$D,3,0)="Debit",D10-E10,E10-D10),IF(VLOOKUP($C10,Chart_of_Accounts!$B:$D,3,0)="Debit",D10-E10,E10-D10)))
A17: =IF(Transactions!A17="","",Transactions!A17) | B17: =Transactions!B17 -> 0 | C17: =Transactions!C17 -> 0 | D17: =Transactions!D17 -> 0 | E17: =Transactions!E17 -> 0 | F17: =IF(OR($A11="",$C11=""),"",IF($C11=$C10,F10+IF(VLOOKUP($C11,Chart_of_Accounts!$B:$D,3,0)="Debit",D11-E11,E11-D11),IF(VLOOKUP($C11,Chart_of_Accounts!$B:$D,3,0)="Debit",D11-E11,E11-D11)))
A18: =IF(Transactions!A18="","",Transactions!A18) | B18: =Transactions!B18 -> 0 | C18: =Transactions!C18 -> 0 | D18: =Transactions!D18 -> 0 | E18: =Transactions!E18 -> 0 | F18: =IF(OR($A12="",$C12=""),"",IF($C12=$C11,F11+IF(VLOOKUP($C12,Chart_of_Accounts!$B:$D,3,0)="Debit",D12-E12,E12-D12),IF(VLOOKUP($C12,Chart_of_Accounts!$B:$D,3,0)="Debit",D12-E12,E12-D12)))
A19: =IF(Transactions!A19="","",Transactions!A19) | B19: =Transactions!B19 -> 0 | C19: =Transactions!C19 -> 0 | D19: =Transactions!D19 -> 0 | E19: =Transactions!E19 -> 0 | F19: =IF(OR($A13="",$C13=""),"",IF($C13=$C12,F12+IF(VLOOKUP($C13,Chart_of_Accounts!$B:$D,3,0)="Debit",D13-E13,E13-D13),IF(VLOOKUP($C13,Chart_of_Accounts!$B:$D,3,0)="Debit",D13-E13,E13-D13)))
B20: =Transactions!B20 -> 0 | C20: =Transactions!C20 -> 0 | D20: =Transactions!D20 -> 0 | E20: =Transactions!E20 -> 0
B21: =Transactions!B21 -> 0 | C21: =Transactions!C21 -> 0 | D21: =Transactions!D21 -> 0 | E21: =Transactions!E21 -> 0
B22: =Transactions!B22 -> 0 | C22: =Transactions!C22 -> 0 | D22: =Transactions!D22 -> 0 | E22: =Transactions!E22 -> 0
B23: =Transactions!B23 -> 0 | C23: =Transactions!C23 -> 0 | D23: =Transactions!D23 -> 0 | E23: =Transactions!E23 -> 0
B24: =Transactions!B24 -> 0 | C24: =Transactions!C24 -> 0 | D24: =Transactions!D24 -> 0 | E24: =Transactions!E24 -> 0
B25: =Transactions!B25 -> 0 | C25: =Transactions!C25 -> 0 | D25: =Transactions!D25 -> 0 | E25: =Transactions!E25 -> 0
B26: =Transactions!B26 -> 0 | C26: =Transactions!C26 -> 0 | D26: =Transactions!D26 -> 0 | E26: =Transactions!E26 -> 0 | F26: =IF(OR($A20="",$C20=""),"",IF($C20=$C19,F19+IF(VLOOKUP($C20,Chart_of_Accounts!$B:$D,3,0)="Debit",D20-E20,E20-D20),IF(VLOOKUP($C20,Chart_of_Accounts!$B:$D,3,0)="Debit",D20-E20,E20-D20)))
B27: =Transactions!B27 -> 0 | C27: =Transactions!C27 -> 0 | D27: =Transactions!D27 -> 0 | E27: =Transactions!E27 -> 0 | F27: =IF(OR($A21="",$C21=""),"",IF($C21=$C20,F20+IF(VLOOKUP($C21,Chart_of_Accounts!$B:$D,3,0)="Debit",D21-E21,E21-D21),IF(VLOOKUP($C21,Chart_of_Accounts!$B:$D,3,0)="Debit",D21-E21,E21-D21)))
B28: =Transactions!B28 -> 0 | C28: =Transactions!C28 -> 0 | D28: =Transactions!D28 -> 0 | E28: =Transactions!E28 -> 0 | F28: =IF(OR($A22="",$C22=""),"",IF($C22=$C21,F21+IF(VLOOKUP($C22,Chart_of_Accounts!$B:$D,3,0)="Debit",D22-E22,E22-D22),IF(VLOOKUP($C22,Chart_of_Accounts!$B:$D,3,0)="Debit",D22-E22,E22-D22)))
B29: =Transactions!B29 -> 0 | C29: =Transactions!C29 -> 0 | D29: =Transactions!D29 -> 0 | E29: =Transactions!E29 -> 0 | F29: =IF(OR($A23="",$C23=""),"",IF($C23=$C22,F22+IF(VLOOKUP($C23,Chart_of_Accounts!$B:$D,3,0)="Debit",D23-E23,E23-D23),IF(VLOOKUP($C23,Chart_of_Accounts!$B:$D,3,0)="Debit",D23-E23,E23-D23)))
B30: =Transactions!B30 -> 0 | C30: =Transactions!C30 -> 0 | D30: =Transactions!D30 -> 0 | E30: =Transactions!E30 -> 0 | F30: =IF(OR($A24="",$C24=""),"",IF($C24=$C23,F23+IF(VLOOKUP($C24,Chart_of_Accounts!$B:$D,3,0)="Debit",D24-E24,E24-D24),IF(VLOOKUP($C24,Chart_of_Accounts!$B:$D,3,0)="Debit",D24-E24,E24-D24)))
B31: =Transactions!B31 -> 0 | C31: =Transactions!C31 -> 0 | D31: =Transactions!D31 -> 0 | E31: =Transactions!E31 -> 0 | F31: =IF(OR($A25="",$C25=""),"",IF($C25=$C24,F24+IF(VLOOKUP($C25,Chart_of_Accounts!$B:$D,3,0)="Debit",D25-E25,E25-D25),IF(VLOOKUP($C25,Chart_of_Accounts!$B:$D,3,0)="Debit",D25-E25,E25-D25)))
B32: =Transactions!B32 -> 0 | C32: =Transactions!C32 -> 0 | D32: =Transactions!D32 -> 0 | E32: =Transactions!E32 -> 0 | F32: =IF(OR($A26="",$C26=""),"",IF($C26=$C25,F25+IF(VLOOKUP($C26,Chart_of_Accounts!$B:$D,3,0)="Debit",D26-E26,E26-D26),IF(VLOOKUP($C26,Chart_of_Accounts!$B:$D,3,0)="Debit",D26-E26,E26-D26)))
B33: =Transactions!B33 -> 0 | C33: =Transactions!C33 -> 0 | D33: =Transactions!D33 -> 0 | E33: =Transactions!E33 -> 0 | F33: =IF(OR($A27="",$C27=""),"",IF($C27=$C26,F26+IF(VLOOKUP($C27,Chart_of_Accounts!$B:$D,3,0)="Debit",D27-E27,E27-D27),IF(VLOOKUP($C27,Chart_of_Accounts!$B:$D,3,0)="Debit",D27-E27,E27-D27)))
B34: =Transactions!B34 -> 0 | C34: =Transactions!C34 -> 0 | D34: =Transactions!D34 -> 0 | E34: =Transactions!E34 -> 0 | F34: =IF(OR($A28="",$C28=""),"",IF($C28=$C27,F27+IF(VLOOKUP($C28,Chart_of_Accounts!$B:$D,3,0)="Debit",D28-E28,E28-D28),IF(VLOOKUP($C28,Chart_of_Accounts!$B:$D,3,0)="Debit",D28-E28,E28-D28)))
B35: =Transactions!B35 -> 0 | C35: =Transactions!C35 -> 0 | D35: =Transactions!D35 -> 0 | E35: =Transactions!E35 -> 0 | F35: =IF(OR($A29="",$C29=""),"",IF($C29=$C28,F28+IF(VLOOKUP($C29,Chart_of_Accounts!$B:$D,3,0)="Debit",D29-E29,E29-D29),IF(VLOOKUP($C29,Chart_of_Accounts!$B:$D,3,0)="Debit",D29-E29,E29-D29)))
B36: =Transactions!B36 -> 0 | C36: =Transactions!C36 -> 0 | D36: =Transactions!D36 -> 0 | E36: =Transactions!E36 -> 0 | F36: =IF(OR($A30="",$C30=""),"",IF($C30=$C29,F29+IF(VLOOKUP($C30,Chart_of_Accounts!$B:$D,3,0)="Debit",D30-E30,E30-D30),IF(VLOOKUP($C30,Chart_of_Accounts!$B:$D,3,0)="Debit",D30-E30,E30-D30)))
B37: =Transactions!B37 -> 0 | C37: =Transactions!C37 -> 0 | D37: =Transactions!D37 -> 0 | E37: =Transactions!E37 -> 0 | F37: =IF(OR($A31="",$C31=""),"",IF($C31=$C30,F30+IF(VLOOKUP($C31,Chart_of_Accounts!$B:$D,3,0)="Debit",D31-E31,E31-D31),IF(VLOOKUP($C31,Chart_of_Accounts!$B:$D,3,0)="Debit",D31-E31,E31-D31)))
... B104: =Transactions!B104 -> 0 | C104: =Transactions!C104 -> 0 | D104: =Transactions!D104 -> 0 | E104: =Transactions!E104 -> 0 | F104: =IF(OR($A98="",$C98=""),"",IF($C98=$C97,F97+IF(VLOOKUP($C98,Chart_of_Accounts!$B:$D,3,0)="Debit",D98-E98,E98-D98),IF(VLOOKUP($C98,Chart_of_Accounts!$B:$D,3,0)="Debit",D98-E98,E98-D98)))

Sheet Trial_Balance
A1: ACME Company Accounting System
A2: Trial Balance
A3: Account | B3: Total Debit | C3: Total Credit
A4: =Chart_of_Accounts!B4 -> Cash | B4: =SUMIF(Transactions!$C:$C,A4,Transactions!$D:$D) -> 0 | C4: =SUMIF(Transactions!$C:$C,A4,Transactions!$E:$E) -> 0
A5: =Chart_of_Accounts!B5 -> Bank | B5: =SUMIF(Transactions!$C:$C,A5,Transactions!$D:$D) -> 0 | C5: =SUMIF(Transactions!$C:$C,A5,Transactions!$E:$E) -> 0
A6: =Chart_of_Accounts!B6 -> Accounts Receivable | B6: =SUMIF(Transactions!$C:$C,A6,Transactions!$D:$D) -> 0 | C6: =SUMIF(Transactions!$C:$C,A6,Transactions!$E:$E) -> 0
A7: =Chart_of_Accounts!B7 -> Inventory | B7: =SUMIF(Transactions!$C:$C,A7,Transactions!$D:$D) -> 0 | C7: =SUMIF(Transactions!$C:$C,A7,Transactions!$E:$E) -> 0
A8: =Chart_of_Accounts!B8 -> Equipment | B8: =SUMIF(Transactions!$C:$C,A8,Transactions!$D:$D) -> 0 | C8: =SUMIF(Transactions!$C:$C,A8,Transactions!$E:$E) -> 0
A9: =Chart_of_Accounts!B9 -> Land | B9: =SUMIF(Transactions!$C:$C,A9,Transactions!$D:$D) -> 0 | C9: =SUMIF(Transactions!$C:$C,A9,Transactions!$E:$E) -> 0
A10: =Chart_of_Accounts!B10 -> Buildings | B10: =SUMIF(Transactions!$C:$C,A10,Transactions!$D:$D) -> 0 | C10: =SUMIF(Transactions!$C:$C,A10,Transactions!$E:$E) -> 0
A11: =Chart_of_Accounts!B11 -> Machinery | B11: =SUMIF(Transactions!$C:$C,A11,Transactions!$D:$D) -> 0 | C11: =SUMIF(Transactions!$C:$C,A11,Transactions!$E:$E) -> 0
A12: =Chart_of_Accounts!B12 -> Accounts Payable | B12: =SUMIF(Transactions!$C:$C,A12,Transactions!$D:$D) -> 0 | C12: =SUMIF(Transactions!$C:$C,A12,Transactions!$E:$E) -> 0
A13: =Chart_of_Accounts!B13 -> Notes Payable | B13: =SUMIF(Transactions!$C:$C,A13,Transactions!$D:$D) -> 0 | C13: =SUMIF(Transactions!$C:$C,A13,Transactions!$E:$E) -> 0
A14: =Chart_of_Accounts!B14 -> Capital | B14: =SUMIF(Transactions!$C:$C,A14,Transactions!$D:$D) -> 0 | C14: =SUMIF(Transactions!$C:$C,A14,Transactions!$E:$E) -> 0
A15: =Chart_of_Accounts!B15 -> Retained Earnings | B15: =SUMIF(Transactions!$C:$C,A15,Transactions!$D:$D) -> 0 | C15: =SUMIF(Transactions!$C:$C,A15,Transactions!$E:$E) -> 0
... A21: =Chart_of_Accounts!B21 -> Supplies Expense | B21: =SUMIF(Transactions!$C:$C,A21,Transactions!$D:$D) -> 0 | C21: =SUMIF(Transactions!$C:$C,A21,Transactions!$E:$E) -> 0
A22: TOTAL | B22: =SUM(B4:B18) -> 0 | C22: =SUM(C4:C18) -> 0
A23: Balance Check | B23: =IF(B22=C22,"Balanced","Not Balanced") -> Balanced

Sheet Income_Statement
A1: ACME Company Accounting System
A2: Income Statement
A3: REVENUE | B3: DR | C3: CR
B4: GH | C4: GH
A5: Sales Revenue | B5: =SUMIF(Transactions!$C:$C,A5,Transactions!$D:$D) -> 0 | C5: =SUMIF(Transactions!$C:$C,A5,Transactions!$E:$E) -> 0
A6: Service Revenue | B6: =SUMIF(Transactions!$C:$C,A6,Transactions!$D:$D) -> 0 | C6: =SUMIF(Transactions!$C:$C,A6,Transactions!$E:$E) -> 0
A7: Total Revenue | C7: =SUM(C5:C6) -> 0
A9: EXPENSES
A10: Rent Expense | B10: =SUMIF(Transactions!$C:$C,A10,Transactions!$D:$D) -> 0 | C10: =SUMIF(Transactions!$C:$C,A10,Transactions!$E:$E) -> 0
A11: Utilities Expense | B11: =SUMIF(Transactions!$C:$C,A11,Transactions!$D:$D) -> 0 | C11: =SUMIF(Transactions!$C:$C,A11,Transactions!$E:$E) -> 0
A12: Salaries Expense | B12: =SUMIF(Transactions!$C:$C,A12,Transactions!$D:$D) -> 0 | C12: =SUMIF(Transactions!$C:$C,A12,Transactions!$E:$E) -> 0
A13: Supplies Expense | B13: =SUMIF(Transactions!$C:$C,A13,Transactions!$D:$D) -> 0 | C13: =SUMIF(Transactions!$C:$C,A13,Transactions!$E:$E) -> 0
A14: Total Expenses | B14: =SUM(B10:B13) -> 0
A16: Net Income | C16: =C7-B14 -> 0

Sheet Balance_Sheet
A1: ACME Company Accounting System
A2: Balance Sheet As at 31st December 2025
A3: ASSETS
A4: Non-current Assets
A5: Equipment | B5: =SUMIF(Transactions!$C:$C,A5,Transactions!$D:$D)-SUMIF(Transactions!$C:$C,A5,Transactions!$E:$E) -> 0
A6: Land | B6: =SUMIF(Transactions!$C:$C,A6,Transactions!$D:$D)-SUMIF(Transactions!$C:$C,A6,Transactions!$E:$E) -> 0
A7: Buildings | B7: =SUMIF(Transactions!$C:$C,A7,Transactions!$D:$D)-SUMIF(Transactions!$C:$C,A7,Transactions!$E:$E) -> 0
A8: Machinery | B8: =SUMIF(Transactions!$C:$C,A8,Transactions!$D:$D)-SUMIF(Transactions!$C:$C,A8,Transactions!$E:$E) -> 0
A9: Total Non-Current Assets | B9: =SUM(B5:B8) -> 0
A11: Current Assets
A12: Cash | B12: =SUMIF(Transactions!$C:$C,A12,Transactions!$D:$D)-SUMIF(Transactions!$C:$C,A12,Transactions!$E:$E) -> 0
A13: Bank | B13: =SUMIF(Transactions!$C:$C,A13,Transactions!$D:$D)-SUMIF(Transactions!$C:$C,A13,Transactions!$E:$E) -> 0
A14: Accounts Receivable | B14: =SUMIF(Transactions!$C:$C,A14,Transactions!$D:$D)-SUMIF(Transactions!$C:$C,A14,Transactions!$E:$E) -> 0
A15: Inventory | B15: =SUMIF(Transactions!$C:$C,A15,Transactions!$D:$D)-SUMIF(Transactions!$C:$C,A15,Transactions!$E:$E) -> 0
A16: Total Current Assets | B16: =SUM(B12:B15) -> 0
A18: TOTAL ASSETS | C18: =B9+B16 -> 0
A20: EQUITY AND LIABILITIES
A21: Equity | B21: =SUMIF(Transactions!$C:$C,A21,Transactions!$E:$E)-SUMIF(Transactions!$C:$C,A21,Transactions!$D:$D) -> 0
A22: Capital | B22: =SUMIF(Transactions!$C:$C,A22,Transactions!$E:$E)-SUMIF(Transactions!$C:$C,A22,Transactions!$D:$D) -> 0
A23: Retained Earnings | B23: =SUMIF(Transactions!$C:$C,A23,Transactions!$E:$E)-SUMIF(Transactions!$C:$C,A23,Transactions!$D:$D) -> 0
A24: Net Income | B24: =Income_Statement!B15 -> 0
A25: Total Equity | B25: =SUM(B22:B24) -> 0
A27: Non-Current Liabilities
A28: Notes Payable | B28: =SUMIF(Transactions!$C:$C,A28,Transactions!$E:$E)-SUMIF(Transactions!$C:$C,A28,Transactions!$D:$D) -> 0
A29: Total Non-Current Liabilities | B29: =B28 -> 0
A31: Current Liabilities
A32: Accounts Payable | B32: =SUMIF(Transactions!$C:$C,A32,Transactions!$E:$E)-SUMIF(Transactions!$C:$C,A32,Transactions!$D:$D) -> 0
A33: Total Current Liabilities | B33: =B32 -> 0
A35: TOTAL LIABILITIES | B35: =B29+B33 -> 0
A37: TOTAL EQUITY AND LIABILITIES | C37: =B25+B35 -> 0
A39: Balance Check | C39: =IF(C18=C37,"Balanced","Not Balanced") -> Balanced

Sheet Dashboard
A1: ACME Company Accounting System
A2: Accounting Dashboard
A4: Total Assets | B4: =Balance_Sheet!B18 -> 0
A5: Total Liabilities | B5: =Balance_Sheet!B35 -> 0
A6: Total Equity | B6: =Balance_Sheet!B25 -> 0
A7: Liabilities + Equity | B7: =Balance_Sheet!C37 -> 0
A8: Balance Status | B8: =Balance_Sheet!C39 -> Balanced
A9: Trial Balance Total Debit | B9: =Trial_Balance!B22 -> 0
A10: Trial Balance Total Credit | B10: =Trial_Balance!C22 -> 0
A11: Net Income | B11: =Income_Statement!C16 -> 0
